django_handleref/__init__.py
django_handleref/admin.py
django_handleref/manager.py
django_handleref/models.py
django_handleref/rest/__init__.py
django_handleref/rest/serializers.py
django_handleref/templates/handleref/grappelli/object_history.html
django_handleref/templates/handleref/grappelli/version_details.html
django_handleref/templates/handleref/grappelli/version_revert.html
django_handleref/templates/handleref/grappelli/version_rollback.html
django_handleref/templates/handleref/object_history.html
django_handleref/templates/handleref/version_details.html
django_handleref/templates/handleref/version_revert.html
django_handleref/templates/handleref/version_rollback.html
django_handleref/util.py
django_handleref/version.py
django_handleref-2.0.0.dist-info/LICENSE.txt
django_handleref-2.0.0.dist-info/WHEEL
django_handleref-2.0.0.dist-info/METADATA
django_handleref-2.0.0.dist-info/RECORD
