Metadata-Version: 2.1
Name: django-handleref
Version: 2.0.0
Summary: django object tracking
Home-page: https://github.com/20c/django-handleref
License: Apache-2.0
Author: 20C
Author-email: code@20c.com
Requires-Python: >=3.8,<4.0
Classifier: Development Status :: 5 - Production/Stable
Classifier: Intended Audience :: Developers
Classifier: License :: OSI Approved :: Apache Software License
Classifier: Programming Language :: Python :: 3
Classifier: Programming Language :: Python :: 3.10
Classifier: Programming Language :: Python :: 3.11
Classifier: Programming Language :: Python :: 3.8
Classifier: Programming Language :: Python :: 3.9
Classifier: Topic :: Software Development
Provides-Extra: docs
Project-URL: Repository, https://github.com/20c/django-handleref
